{
    "dt-id": "https://dtid.org/2021-04-28_08-34-42_c0daef20",
    "hosting-iri": "https://testbase.dtp.fi/2021-04-28_08-34-42_c0daef20",
    "name": "Tactful Rough Ant Of Perfection",
    "description": "Amet non consectetur etincidunt est.",
    "relations": [
        {
            "dt-id": "https://dtid.org/2021-04-28_08-34-42_a055668f",
            "relationType": "parent"
        },
        {
            "dt-id": "https://dtid.org/2021-04-28_08-34-42_6799b8cc",
            "relationType": "child"
        },
        {
            "dt-id": "https://dtid.org/2021-04-28_08-34-42_ab18dbda",
            "relationType": "child"
        },
        {
            "dt-id": "https://dtid.org/2021-04-28_08-34-42_996b7d2b",
            "relationType": "child"
        }
    ],
    "baseurl": "https://testbase.dtp.fi",
    "edit": "https://github.com/juusoautiosalo/twinbase-measurement-planning/edit/main/docs/2021-04-28_08-34-42_c0daef20/index.yaml"
}